LICENSE.md
README.md
setup.py
vsv/__init__.py
vsv/ddb.py
vsv/dv.py
vsv/idb.py
vsv/new.py
vsv/qdb.py
vsv/sdb.py
vsv.egg-info/PKG-INFO
vsv.egg-info/SOURCES.txt
vsv.egg-info/dependency_links.txt
vsv.egg-info/requires.txt
vsv.egg-info/top_level.txt