Metadata-Version: 2.1
Name: vsv
Version: 1.0.3
Summary: From Team of Audio Signature Generators, VKK Mulukutla, S Midatani, VVK Kareti.
License-File: LICENSE.md
